<pkgref spec="1.12" uuid="59E9311E-92C2-4533-8EDD-64439CCABC11"><config><identifier>org.sourceforge.installGemrb.PLTImporter.pkg</identifier><version>1.0</version><description/><post-install type="none"/><requireAuthorization/><installFrom relative="true" mod="true">build/PLTImporter.so</installFrom><installTo mod="true">/Library/Application Support/GemRB/plugins</installTo><flags><followSymbolicLinks/></flags><packageStore type="internal"/><mod>installTo.path</mod><mod>installFrom.path</mod><mod>parent</mod><mod>installTo</mod></config><contents><file-list>28pltimporter-contents.xml</file-list><filter>/CVS$</filter><filter>/\.svn$</filter><filter>/\.cvsignore$</filter><filter>/\.cvspass$</filter><filter>/\.DS_Store$</filter></contents></pkgref>